mogdevice/__init__.py
mogdevice/mogdevice.py
mogdevice/qrf.py
mogdevice/utils.py
mogdevice-1.2.1.dist-info/LICENSE
mogdevice-1.2.1.dist-info/METADATA
mogdevice-1.2.1.dist-info/WHEEL
mogdevice-1.2.1.dist-info/top_level.txt
mogdevice-1.2.1.dist-info/RECORD
