Metadata-Version: 2.1
Name: mogdevice
Version: 1.2.1
Summary: Communicating with MOGlabs devices
Author: Bastian Leykauf
Author-email: leykauf@physik.hu-berlin.de
License: Copyright (c) 2017 - present, MOG Laboratories Pty Ltd, Australia.
Project-URL: homepage, https://github.com/bleykauf/mogdevice/
Project-URL: repository, https://github.com/bleyakauf/mogdevice/
Classifier: Programming Language :: Python :: 3
Classifier: License :: OSI Approved :: MIT License
Classifier: Operating System :: OS Independent
Classifier: Intended Audience :: Science/Research
Requires-Python: >=3.8
License-File: LICENSE
Requires-Dist: serial >=0.0.97
Provides-Extra: dev
Requires-Dist: black >=22.8.0 ; extra == 'dev'
Requires-Dist: pre-commit >=2.20.0 ; extra == 'dev'
Requires-Dist: flake8 >=5.0.4 ; extra == 'dev'
Requires-Dist: isort >=5.10.1 ; extra == 'dev'
Requires-Dist: flake8-pyproject >=1.2.3 ; extra == 'dev'
